skyflow/__init__.py
skyflow/client/__init__.py
skyflow/client/skyflow.py
skyflow/error/__init__.py
skyflow/error/_skyflow_error.py
skyflow/generated/__init__.py
skyflow/generated/rest/__init__.py
skyflow/generated/rest/client.py
skyflow/generated/rest/environment.py
skyflow/generated/rest/py.typed
skyflow/generated/rest/version.py
skyflow/generated/rest/audit/__init__.py
skyflow/generated/rest/audit/client.py
skyflow/generated/rest/audit/raw_client.py
skyflow/generated/rest/audit/types/__init__.py
skyflow/generated/rest/audit/types/audit_service_list_audit_events_request_filter_ops_action_type.py
skyflow/generated/rest/audit/types/audit_service_list_audit_events_request_filter_ops_context_access_type.py
skyflow/generated/rest/audit/types/audit_service_list_audit_events_request_filter_ops_context_actor_type.py
skyflow/generated/rest/audit/types/audit_service_list_audit_events_request_filter_ops_context_auth_mode.py
skyflow/generated/rest/audit/types/audit_service_list_audit_events_request_filter_ops_resource_type.py
skyflow/generated/rest/audit/types/audit_service_list_audit_events_request_sort_ops_order_by.py
skyflow/generated/rest/authentication/__init__.py
skyflow/generated/rest/authentication/client.py
skyflow/generated/rest/authentication/raw_client.py
skyflow/generated/rest/bin_lookup/__init__.py
skyflow/generated/rest/bin_lookup/client.py
skyflow/generated/rest/bin_lookup/raw_client.py
skyflow/generated/rest/core/__init__.py
skyflow/generated/rest/core/api_error.py
skyflow/generated/rest/core/client_wrapper.py
skyflow/generated/rest/core/datetime_utils.py
skyflow/generated/rest/core/file.py
skyflow/generated/rest/core/force_multipart.py
skyflow/generated/rest/core/http_client.py
skyflow/generated/rest/core/http_response.py
skyflow/generated/rest/core/jsonable_encoder.py
skyflow/generated/rest/core/pydantic_utilities.py
skyflow/generated/rest/core/query_encoder.py
skyflow/generated/rest/core/remove_none_from_dict.py
skyflow-2.0.0.dist-info/licenses/LICENSE
skyflow-2.0.0.dist-info/METADATA
skyflow-2.0.0.dist-info/WHEEL
skyflow-2.0.0.dist-info/top_level.txt
skyflow-2.0.0.dist-info/RECORD
